Metadata-Version: 2.1
Name: vodou-aws-mfa
Version: 0.0.15
Summary: Manage AWS MFA Security Credentials
Home-page: https://github.com/vodou/aws-mfa
Author: Fritz Sassine
Author-email: fileunderdonotread@gmail.com
License: MIT
Platform: UNKNOWN
